{
  "exp_name": "",
  "multi_exp_name": "llicti_ppr3_mdl4gmm5_YCoCg_scl0tttt_mwsaSEP_Chs88_Lys3_E4O3_combnlyrs1tolF_clrjnt2_combsclT__ps160bs64x1_lr1",
  "agent": "LLICTIAgent",
  "mode": "eval_model",
  "resume_training": false,
  "cuda": true,
  "gpu_device": 0,
  "seed": 1337,



  "ycocg": true,
  "clrchs": 3,
  "clr_joint_mode": 2,
  "clrjnt0seqmd": false,
  "mwsa_joint": false,
  "chs": [88, 1, 1, 1, 1],
  "conv_layers": 3,
  "combine_layers1toL": false,
  "Evens": [4, 4, 4, 4, 4],
  "Odds": [3, 3, 3, 3, 3],
  "dwtlevels": [0, 1, 2, 3, 4],
  "useprevlevNN": [false, true, true, true, true],
  "wtr_type": "lazydwt",
  "net_type": "regular",
  "lif_prec_bits": 8,
  "ent_mdl_num": 4,
  "activfun": "ReLU",
  "subtract_mean": false,
  "distribution": "normal",
  "num_mixtures": 5,

  "batch_size": 32,
  "patches_per_img": 1,
  "patch_size": 160,
  "dl_numworkers": 3,
  "grad_acc_iters": 2,
  "loss_prnt_iters": 2000,
  "val_batch_size": 1,
  "val_patch_size": 0,
  "multi_agent":true,
  "multi_param":"lambda_",
  "learning_rate":1.0e-4,

  "gamma": 1.00,
  "lambda_": [0],
  "max_epoch": 45,
  "log_interval": 20,
  "validate_every": 1,
  "test_every": 2,
  "checkpoint_file": "checkpoint.pth.tar",

  "num_train_dirs" :1,
  "train_data_1": "/media/datas/OpenImages-L3C-train_oi_divby2x2_prll",
  "train_data_2": "/media/datas/CLIC_train_professional_2020_256x256",
  "train_data_3": "/media/datas/CLIC_train_mobile_2020_256x256",
  "train_data_4": "/media/datas/CLIC_train",
  "test_data": "/media/datas/OpenImages-L3C",
  "valid_data": "/media/datas/OpenImages-L3C"
}
